cachify/__init__.py
cachify/cache.py
cachify/config/__init__.py
cachify/features/__init__.py
cachify/features/never_die.py
cachify/memory_cache.py
cachify/redis/__init__.py
cachify/redis/config.py
cachify/redis/lock.py
cachify/redis_cache.py
cachify/storage/__init__.py
cachify/storage/memory_storage.py
cachify/storage/redis_storage.py
cachify/types/__init__.py
cachify/utils/__init__.py
cachify/utils/arguments.py
cachify/utils/errors.py
cachify/utils/functions.py
cachify/utils/hash.py
cachify-0.3.0.dist-info/METADATA
cachify-0.3.0.dist-info/WHEEL
cachify-0.3.0.dist-info/entry_points.txt
cachify-0.3.0.dist-info/licenses/LICENSE
cachify-0.3.0.dist-info/RECORD
