Metadata-Version: 2.4
Name: cachify
Version: 0.3.0
Summary: A simple cache library with sync/async support, Memory and Redis backend
License: MIT
License-File: LICENSE
Keywords: cachify,cache,caching,redis,async,decorator,memoization
Author: dynalz
Author-email: git@pulsar.finance
Requires-Python: >=3.10,<3.15
Classifier: Development Status :: 4 - Beta
Classifier: Intended Audience :: Developers
Classifier: License :: OSI Approved :: MIT License
Classifier: Programming Language :: Python :: 3
Classifier: Programming Language :: Python :: 3.10
Classifier: Programming Language :: Python :: 3.11
Classifier: Programming Language :: Python :: 3.12
Classifier: Programming Language :: Python :: 3.13
Classifier: Programming Language :: Python :: 3.14
Classifier: Topic :: Software Development :: Libraries :: Python Modules
Classifier: Typing :: Typed
Requires-Dist: redis[hiredis] (>5.0.0)
Project-URL: Homepage, https://github.com/PulsarDataSolutions/cachify
Project-URL: Repository, https://github.com/PulsarDataSolutions/cachify
